primapy_stargate/__init__.py
primapy_stargate/hub/README.md
primapy_stargate/hub/__init__.py
primapy_stargate/hub/app.py
primapy_stargate/model/README.md
primapy_stargate/model/__init__.py
primapy_stargate/oracle/README.md
primapy_stargate/oracle/__init__.py
primapy_stargate-0.1.0.dist-info/WHEEL
primapy_stargate-0.1.0.dist-info/METADATA
primapy_stargate-0.1.0.dist-info/RECORD
