Metadata-Version: 2.1
Name: primapy-stargate
Version: 0.1.0
Summary: Hub for Oracles
Author: Team AMOps
Author-email: amops@prima.it
Requires-Python: >=3.8,<4.0
Classifier: Programming Language :: Python :: 3
Classifier: Programming Language :: Python :: 3.10
Classifier: Programming Language :: Python :: 3.8
Classifier: Programming Language :: Python :: 3.9
Requires-Dist: fastapi (>=0.68.1,<0.69.0)
Requires-Dist: uvicorn (>=0.15.0,<0.16.0)
